{
  "version": "3.0",
  "lastUpdated": "2026-04-21T15:30:00.000Z",
  "activeFeatures": [],
  "primaryFeature": null,
  "lastPhaseTransition": "report → archived (2026-04-21, qr-scanner-ui-ux matchRate 92, FR 19/20)",
  "features": {},
  "pipeline": {
    "currentPhase": 1,
    "level": "Dynamic",
    "phaseHistory": []
  },
  "session": {
    "startedAt": "2026-04-09T06:11:12.207Z",
    "onboardingCompleted": false,
    "lastActivity": "2026-04-21T13:07:54.333Z"
  },
  "history": [
    {
      "timestamp": "2026-04-21T05:40:00.000Z",
      "feature": "cleanup",
      "phase": "admin",
      "action": "removed 14 entries (12 archived + scripts + Temp), reset activeFeatures/primaryFeature"
    },
    {
      "timestamp": "2026-04-21T05:45:00.000Z",
      "feature": "color-tab-redesign",
      "phase": "archived",
      "action": "moved 4 docs to docs/archive/2026-04/color-tab-redesign/"
    },
    {
      "timestamp": "2026-04-21T05:55:00.000Z",
      "feature": "refactor-qr-shape-tab",
      "phase": "archived",
      "action": "Plan only archived — implementation already done via part of pattern (aligned with R-series); closed without Design/Analysis/Report"
    },
    {
      "timestamp": "2026-04-21T06:00:00.000Z",
      "feature": "user-management",
      "phase": "archived",
      "action": "Plan+Design+Analysis archived (matchRate 91%, FR-01~08) — Report skipped"
    },
    {
      "timestamp": "2026-04-21T15:30:00.000Z",
      "feature": "qr-scanner-ui-ux",
      "phase": "archived",
      "action": "Plan+Design+Analysis+Report archived (matchRate 92%, 33 new files, R-series 8/8) → docs/archive/2026-04/qr-scanner-ui-ux/"
    }
  ],
  "stateMachine": {
    "defaultWorkflow": "default",
    "activeWorkflows": {},
    "totalTransitions": 0
  },
  "automation": {
    "globalLevel": 2,
    "trustScore": 40,
    "pendingApprovals": 0,
    "lastGateResult": null
  },
  "team": {
    "enabled": true,
    "stateFile": ".bkit/runtime/agent-state.json",
    "eventsFile": ".bkit/runtime/agent-events.jsonl"
  }
}